{
  "date": "2025-06-24",
  "type": "special",
  "url": "https://berkeleyca.gov/city-council-special-meeting-eagenda-june-24-2025",
  "fetched": "2026-04-09T07:38:36.798470",
  "consent_items": [],
  "action_items": [
    {
      "number": 1,
      "section": "action",
      "title": "Fire Permit and Inspection Fee Schedule",
      "from_raw": "City Manager",
      "authors": [],
      "cosponsors": [],
      "commission": "City Manager",
      "recommendation": "Conduct a public hearing and upon conclusion, adopt a Resolution: 1. Approving a revised Fire Department fee schedule which incorporates an increase in fire permitting and fire inspection fees from $392.00 to $500.00 per hour; and 2. Adding fees to construction and operational permit fees that were new permits from the California Fire Code (CFC) in years 2016, 2019, and 2022, which were adopted with no fee assigned; and 3. Adding a fee amount to the operational permit for Class IIIB Combustible ",
      "financial_raw": "See report",
      "financial_none": false,
      "financial_staff_time": false,
      "dollar_total": 892,
      "discretionary": {},
      "off_mission": false,
      "off_mission_reasons": [],
      "false_fiscal": false
    },
    {
      "number": 2,
      "section": "action",
      "title": "New Fee Schedule for Carry Concealed Weapon Permits",
      "from_raw": "City Manager",
      "authors": [],
      "cosponsors": [],
      "commission": "City Manager",
      "recommendation": "Conduct a public hearing and upon conclusion, adopt a Resolution establishing a new fee schedule (effective July 1, 2025) to support application processing, background investigations, and license issuance for Carry Concealed Weapon Permits.",
      "financial_raw": "See report",
      "financial_none": false,
      "financial_staff_time": false,
      "dollar_total": 0,
      "discretionary": {},
      "off_mission": false,
      "off_mission_reasons": [],
      "false_fiscal": false
    },
    {
      "number": 3,
      "section": "action",
      "title": "Changes to Select Public Works Transportation Permit Fees",
      "from_raw": "City Manager",
      "authors": [],
      "cosponsors": [],
      "commission": "City Manager",
      "recommendation": "Conduct a public hearing and upon conclusion, adopt a Resolution increasing fees for parking permits, rescinding Resolution No. 68,344-N.S.",
      "financial_raw": "See report",
      "financial_none": false,
      "financial_staff_time": false,
      "dollar_total": 0,
      "discretionary": {},
      "off_mission": false,
      "off_mission_reasons": [],
      "false_fiscal": false
    },
    {
      "number": 4,
      "section": "action",
      "title": "Selected Marina Fee Increases",
      "from_raw": "City Manager",
      "authors": [],
      "cosponsors": [],
      "commission": "City Manager",
      "recommendation": "Conduct a public hearing and upon conclusion, adopt a Resolution approving new fees and increasing current fees for select Marina fees; and rescinding Resolution No. 70,868-N.S. and all amendatory resolutions.",
      "financial_raw": "See report.",
      "financial_none": false,
      "financial_staff_time": false,
      "dollar_total": 0,
      "discretionary": {},
      "off_mission": false,
      "off_mission_reasons": [],
      "false_fiscal": false
    }
  ],
  "n_consent": 0,
  "n_off_mission": 0,
  "n_false_fiscal": 0
}